jeremy_poetry_test/__init__.py
jeremy_poetry_test/main.py
jeremy_poetry_test/things/__init__.py
jeremy_poetry_test-0.1.13.dist-info/WHEEL
jeremy_poetry_test-0.1.13.dist-info/METADATA
jeremy_poetry_test-0.1.13.dist-info/RECORD
